{"type": "FeatureCollection", "id": "http://archaeology.link/ontology#ExcuvationSite", "name": "ExcuvationSite", "features": [{"type": "Feature", "id": "http://data.archaeology.link/data/bb5kbc/loc_693", "name": "Location 1", "dateprops": [], "properties": {"http://archaeoinformatics.link/ontology#siteType": ["http://archaeoinformatics.link/ontology#ArchaeologicalSite"], "http://archaeology.link/ontology#hasFlurname": ["Test 1"], "http://archaeology.link/ontology#hasGemarkung": ["Gem 1"], "http://archaeology.link/ontology#hasLocationType": ["Typ 1"], "http://archaeology.link/ontology#hasType": ["http://archaeology.link/ontology#ExcuvationSite"], "http://purl.org/dc/terms/creator": ["https://orcid.org/0000-0002-3246-3531", "https://orcid.org/0000-0003-4696-2101"], "http://purl.org/dc/terms/license": ["https://creativecommons.org/licenses/by/4.0/"], "http://purl.org/dc/terms/rightsHolder": ["https://orcid.org/0000-0002-3246-3531", "https://orcid.org/0000-0003-4696-2101"], "http://www.opengis.net/ont/geosparql#hasGeometry": ["http://data.archaeology.link/data/bb5kbc/loc_693_geom"], "http://www.w3.org/1999/02/22-rdf-syntax-ns#type": ["http://archaeology.link/ontology#Location", "http://www.w3.org/ns/prov#Entity", "http://archaeoinformatics.link/ontology#Site"], "http://www.w3.org/2000/01/rdf-schema#label": ["Location 1"], "http://www.w3.org/ns/prov#wasAttributedTo": ["https://github.com/Research-Squirrel-Engineers/bb-5kbc/blob/main/py/fundplatz.py"], "http://www.w3.org/ns/prov#wasDerivedFrom": ["https://github.com/Research-Squirrel-Engineers/bb-5kbc"], "http://www.w3.org/ns/prov#wasGeneratedBy": ["http://data.archaeology.link/data/bb5kbc/loc_693_pyscript"]}, "geometry": {"type": "Point", "coordinates": [18.4815, 42.779], "crs": "4326"}}], "numberMatched": 1, "numberReturned": 1, "bbox": [18.4815, 42.779, 18.4815, 42.779], "crs": "http://www.opengis.net/def/crs/EPSG/0/4326"}